breadmake/__init__.py
breadmake/breadmake_cli.py
breadmake/core.py
breadmake-0.1.0.dist-info/METADATA
breadmake-0.1.0.dist-info/WHEEL
breadmake-0.1.0.dist-info/entry_points.txt
breadmake-0.1.0.dist-info/top_level.txt
breadmake-0.1.0.dist-info/RECORD
